nanook/__init__.py
nanook/controller.py
nanook/midi/constants.py
nanook/midi/device.py
nanook/midi/utils.py
nanook/nktrl_st_file.py
nanook/scene.py
nanook/scripts/cli.py
nanook/scripts/curses_ui.py
nanook/sniffer.py
nanook-0.1.2.dist-info/entry_points.txt
nanook-0.1.2.dist-info/WHEEL
nanook-0.1.2.dist-info/METADATA
nanook-0.1.2.dist-info/RECORD
