Metadata-Version: 2.1
Name: nanook
Version: 0.1.2
Summary: Command line tool for managing scenes on the KORG nanoKONTROL Studio MIDI controller.
Home-page: https://github.com/miklosaubert/nanook
License: Unlicense
Keywords: MIDI,controller,CLI,manager
Author: Miklos Aubert
Author-email: miklos.aubert@gmail.com
Requires-Python: >=3.9,<4.0
Classifier: Development Status :: 3 - Alpha
Classifier: License :: OSI Approved :: The Unlicense (Unlicense)
Classifier: License :: Other/Proprietary License
Classifier: Programming Language :: Python :: 3
Classifier: Programming Language :: Python :: 3.9
Classifier: Topic :: Multimedia :: Sound/Audio :: MIDI
Requires-Dist: aioconsole (>=0.3.1,<0.4.0)
Requires-Dist: click (>=7.1.2,<8.0.0)
Requires-Dist: mido (>=1.2.9,<2.0.0)
Requires-Dist: python-rtmidi (>=1.4.9,<2.0.0)
Requires-Dist: uvloop (>=0.15.2,<0.16.0)
Project-URL: Repository, https://github.com/miklosaubert/nanook
